{
    "categories":[
        {
            "name":"Vetements",
            "img":"cate-1.svg"
        },
        {
            "name":"Electroniques",
            "img":"cate-2.svg"
        },
        {
            "name":"Autres",
            "img":"cate-10.svg"
        }
    ],
    "vetements":[
        {
            "name":"casquette",
            "img":"slide-1.png",
            "price":29,
            "quantity_available":19
        },
        {
            "name":"chaussure",
            "img":"slide-2.png",
            "price":200,
            "quantity_available":0
        },
        {
            "name":"pull",
            "img":"slide-3.png",
            "price":9,
            "quantity_available":7
        }
    ],

    "electroniques":[
        {
            "name":"lunnette",
            "img":"elec-1.png",
            "price":800,
            "quantity_available":4
        },
        {
            "name":"airpode",
            "img":"elec-2.png",
            "price":70,
            "quantity_available":9
        },
        {
            "name":"smartphone",
            "img":"elec-3.png",
            "price":110,
            "quantity_available":30
        }
    ],

    "autres":[
        {
            "name":"plante",
            "img":"arrivals1.png",
            "price":90,
            "quantity_available":1
        },
        {
            "name":"rouge au levre",
            "img":"arrivals2.png",
            "price":40,
            "quantity_available":4
        },
        {
            "name":"jeux",
            "img":"arrivals3.png",
            "price":108,
            "quantity_available":0
        }
        
    ]


}